gino_factory/__init__.py
gino_factory/factory.py
gino_factory/faker.py
gino_factory/proxy.py
gino_factory/utils.py
tests/__init__.py
tests/conftest.py
tests/models.py
tests/test_common.py
tests/test_tree.py
gino_factory-0.1.0.dist-info/LICENSE.txt
gino_factory-0.1.0.dist-info/METADATA
gino_factory-0.1.0.dist-info/WHEEL
gino_factory-0.1.0.dist-info/top_level.txt
gino_factory-0.1.0.dist-info/RECORD
