Metadata-Version: 2.1
Name: gino-factory
Version: 0.1.0
Summary: Gino Factory
Home-page: UNKNOWN
Author: Basalex (Alexander Baskakov)
Author-email: <alexanderbaskakov@mail.ru>
License: UNKNOWN
Project-URL: Source, https://github.com/Basalex/gino_factory
Keywords: python,gino>=1.01,faker>=4.0.1
Platform: UNKNOWN
Classifier: Development Status :: 4 - Beta
Classifier: Intended Audience :: Developers
Classifier: Programming Language :: Python :: 3
Classifier: Operating System :: Unix
Classifier: Operating System :: MacOS :: MacOS X
Classifier: Operating System :: Microsoft :: Windows
License-File: LICENSE.txt
Requires-Dist: gino
Requires-Dist: faker
